wb_looker/__init__.py
wb_looker/client.py
wb_looker/const.py
wb_looker/models.py
wb_looker-0.0.3.dist-info/LICENSE
wb_looker-0.0.3.dist-info/METADATA
wb_looker-0.0.3.dist-info/WHEEL
wb_looker-0.0.3.dist-info/top_level.txt
wb_looker-0.0.3.dist-info/RECORD
