Metadata-Version: 2.1
Name: wb-looker
Version: 0.0.3
Summary: Small async wildberries api-client
Author-email: Dmitry Kurchigin <kurchigin.dmitry@yandex.ru>
Project-URL: Homepage, https://github.com/dkurchigin/wb_looker
Project-URL: Bug Tracker, https://github.com/dkurchigin/wb_looker/issues
Classifier: Programming Language :: Python :: 3
Classifier: License :: OSI Approved :: MIT License
Classifier: Operating System :: OS Independent
Requires-Python: >=3.7
License-File: LICENSE
